odoo/addons/pms_hr_property/README.rst
odoo/addons/pms_hr_property/__init__.py
odoo/addons/pms_hr_property/__manifest__.py
odoo/addons/pms_hr_property/i18n/de.po
odoo/addons/pms_hr_property/i18n/it.po
odoo/addons/pms_hr_property/i18n/pms_hr_property.pot
odoo/addons/pms_hr_property/models/__init__.py
odoo/addons/pms_hr_property/models/hr_employee.py
odoo/addons/pms_hr_property/models/pms_property.py
odoo/addons/pms_hr_property/readme/CONTRIBUTORS.rst
odoo/addons/pms_hr_property/readme/CREDITS.rst
odoo/addons/pms_hr_property/readme/DESCRIPTION.rst
odoo/addons/pms_hr_property/static/description/icon.png
odoo/addons/pms_hr_property/static/description/index.html
odoo/addons/pms_hr_property/tests/__init__.py
odoo/addons/pms_hr_property/tests/test_pms_hr_property.py
odoo/addons/pms_hr_property/views/hr_employee_view.xml
odoo/addons/pms_hr_property/views/pms_hr_property_view.xml
odoo_addon_pms_hr_property-16.0.1.0.0.6.dist-info/METADATA
odoo_addon_pms_hr_property-16.0.1.0.0.6.dist-info/WHEEL
odoo_addon_pms_hr_property-16.0.1.0.0.6.dist-info/top_level.txt
odoo_addon_pms_hr_property-16.0.1.0.0.6.dist-info/RECORD
