Metadata-Version: 2.1
Name: odoo-addon-pms_hr_property
Version: 16.0.1.0.0.6
Summary: Adds to the employee the property on which he works.
Home-page: https://github.com/OCA/pms
Author: OsoTranquilo,Odoo Community Association (OCA)
Author-email: support@odoo-community.org
License: AGPL-3
Classifier: Programming Language :: Python
Classifier: Framework :: Odoo
Classifier: Framework :: Odoo :: 16.0
Classifier: License :: OSI Approved :: GNU Affero General Public License v3
Requires-Python: >=3.10
Requires-Dist: odoo-addon-pms<16.1dev,>=16.0dev
Requires-Dist: odoo<16.1dev,>=16.0a
